{
    "version": 0.1,
    "data": [
        {
            "id": "LONG_5a6cef0c-175d-4779-bfd4-f7b193fb9039",
            "length_category": "LONG",
            "length": 449.88780331611633,
            "start_time": 1673884532.773957,
            "end_time": 1673884982.6617603,
            "file_info": {
                "qa_start_filename": "1673884531.323784.pkl",
                "qa_end_filename": "1673884981.262587.pkl"
            }
        },
        {
            "id": "LONG_8f32d561-e898-453c-ae99-2e53745389e1",
            "length_category": "LONG",
            "length": 521.9491529464722,
            "start_time": 1673884331.153418,
            "end_time": 1673884853.102571,
            "file_info": {
                "qa_start_filename": "1673884329.703198.pkl",
                "qa_end_filename": "1673884851.752448.pkl"
            }
        },
        {
            "id": "LONG_cbe5ca33-b001-47c4-9397-aca6d275e5e4",
            "length_category": "LONG",
            "length": 684.8592975139618,
            "start_time": 1673884316.1515949,
            "end_time": 1673885001.0108924,
            "file_info": {
                "qa_start_filename": "1673884314.701463.pkl",
                "qa_end_filename": "1673884999.657634.pkl"
            }
        },
        {
            "id": "LONG_115fe136-a8ee-43f7-858d-a0a357c03fad",
            "length_category": "LONG",
            "length": 494.94618034362793,
            "start_time": 1673884349.1557107,
            "end_time": 1673884844.101891,
            "file_info": {
                "qa_start_filename": "1673884347.705484.pkl",
                "qa_end_filename": "1673884842.751738.pkl"
            }
        },
        {
            "id": "LONG_7213d1b5-0f7a-4361-b779-c6689042ae8a",
            "length_category": "LONG",
            "length": 722.968642950058,
            "start_time": 1673884205.1412687,
            "end_time": 1673884928.1099117,
            "file_info": {
                "qa_start_filename": "1673884203.691077.pkl",
                "qa_end_filename": "1673884926.759779.pkl"
            }
        },
        {
            "id": "LONG_74167a94-2255-4d16-bb78-db37801acc0a",
            "length_category": "LONG",
            "length": 608.9567198753357,
            "start_time": 1673884337.1544888,
            "end_time": 1673884946.1112087,
            "file_info": {
                "qa_start_filename": "1673884335.704203.pkl",
                "qa_end_filename": "1673884944.76106.pkl"
            }
        },
        {
            "id": "LONG_f4661173-26c9-4939-824c-a238736d53ef",
            "length_category": "LONG",
            "length": 554.6039714813232,
            "start_time": 1673884235.1443243,
            "end_time": 1673884789.7482958,
            "file_info": {
                "qa_start_filename": "1673884233.694191.pkl",
                "qa_end_filename": "1673884788.348729.pkl"
            }
        },
        {
            "id": "LONG_242c13b6-b47f-4022-9697-02611d770526",
            "length_category": "LONG",
            "length": 581.9552934169769,
            "start_time": 1673884325.152643,
            "end_time": 1673884907.1079364,
            "file_info": {
                "qa_start_filename": "1673884323.702449.pkl",
                "qa_end_filename": "1673884905.757789.pkl"
            }
        },
        {
            "id": "LONG_82e9a231-76cf-446e-9a04-4afd6c831b2d",
            "length_category": "LONG",
            "length": 594.6468923091888,
            "start_time": 1673884409.413914,
            "end_time": 1673885004.0608063,
            "file_info": {
                "qa_start_filename": "1673884407.913838.pkl",
                "qa_end_filename": "1673885002.66134.pkl"
            }
        },
        {
            "id": "LONG_38a496dc-1afd-4e26-b8b2-c6640cab0499",
            "length_category": "LONG",
            "length": 575.9545788764954,
            "start_time": 1673884268.1473122,
            "end_time": 1673884844.101891,
            "file_info": {
                "qa_start_filename": "1673884266.697187.pkl",
                "qa_end_filename": "1673884842.751738.pkl"
            }
        },
        {
            "id": "MEDIUM_3373f674-4a26-465b-9a08-8ca73651a0af",
            "length_category": "MEDIUM",
            "length": 129.62322688102722,
            "start_time": 1673884590.280919,
            "end_time": 1673884719.904146,
            "file_info": {
                "qa_start_filename": "1673884588.830469.pkl",
                "qa_end_filename": "1673884718.554022.pkl"
            }
        },
        {
            "id": "MEDIUM_28199d34-e26c-4b79-8775-943431d3a68a",
            "length_category": "MEDIUM",
            "length": 286.284930229187,
            "start_time": 1673884319.1519153,
            "end_time": 1673884605.4368455,
            "file_info": {
                "qa_start_filename": "1673884317.701719.pkl",
                "qa_end_filename": "1673884604.037266.pkl"
            }
        },
        {
            "id": "MEDIUM_afd2f89f-f0b9-4082-9136-e2122475c3cd",
            "length_category": "MEDIUM",
            "length": 217.18056511878967,
            "start_time": 1673884409.413914,
            "end_time": 1673884626.594479,
            "file_info": {
                "qa_start_filename": "1673884407.913838.pkl",
                "qa_end_filename": "1673884625.245187.pkl"
            }
        },
        {
            "id": "MEDIUM_02da6f10-4ce1-4eb3-a416-c4522e9c8133",
            "length_category": "MEDIUM",
            "length": 389.33634853363037,
            "start_time": 1673884457.765781,
            "end_time": 1673884847.1021295,
            "file_info": {
                "qa_start_filename": "1673884456.315665.pkl",
                "qa_end_filename": "1673884845.752014.pkl"
            }
        },
        {
            "id": "MEDIUM_9595c924-7840-4964-8bd0-d6e3080bcd65",
            "length_category": "MEDIUM",
            "length": 311.2295618057251,
            "start_time": 1673884514.771724,
            "end_time": 1673884826.0012858,
            "file_info": {
                "qa_start_filename": "1673884513.321656.pkl",
                "qa_end_filename": "1673884824.650921.pkl"
            }
        },
        {
            "id": "MEDIUM_11801608-016d-4367-8247-4a885afef25d",
            "length_category": "MEDIUM",
            "length": 189.9626317024231,
            "start_time": 1673884801.8985457,
            "end_time": 1673884991.8611774,
            "file_info": {
                "qa_start_filename": "1673884800.448579.pkl",
                "qa_end_filename": "1673884990.460157.pkl"
            }
        },
        {
            "id": "MEDIUM_022ee3b7-38a6-4a36-9f48-fa656ea3cf21",
            "length_category": "MEDIUM",
            "length": 310.828489780426,
            "start_time": 1673884581.2777796,
            "end_time": 1673884892.1062694,
            "file_info": {
                "qa_start_filename": "1673884579.827572.pkl",
                "qa_end_filename": "1673884890.756073.pkl"
            }
        },
        {
            "id": "MEDIUM_b5b98312-f881-422d-b2cb-4b9c5696948b",
            "length_category": "MEDIUM",
            "length": 186.76357674598694,
            "start_time": 1673884795.8981836,
            "end_time": 1673884982.6617603,
            "file_info": {
                "qa_start_filename": "1673884794.448126.pkl",
                "qa_end_filename": "1673884981.262587.pkl"
            }
        },
        {
            "id": "MEDIUM_c6c87c47-04c3-44ca-a1be-053153b740c5",
            "length_category": "MEDIUM",
            "length": 281.0075514316559,
            "start_time": 1673884713.9035764,
            "end_time": 1673884994.9111278,
            "file_info": {
                "qa_start_filename": "1673884712.453442.pkl",
                "qa_end_filename": "1673884993.55943.pkl"
            }
        },
        {
            "id": "MEDIUM_254c3f52-e4ed-4828-ba85-42a500ff8676",
            "length_category": "MEDIUM",
            "length": 123.66027760505676,
            "start_time": 1673884602.387374,
            "end_time": 1673884726.0476515,
            "file_info": {
                "qa_start_filename": "1673884600.936982.pkl",
                "qa_end_filename": "1673884724.649261.pkl"
            }
        },
        {
            "id": "SHORT_39a4eb19-b64e-4289-abcf-92ea6c3debba",
            "length_category": "SHORT",
            "length": 81.9946072101593,
            "start_time": 1673884713.9035764,
            "end_time": 1673884795.8981836,
            "file_info": {
                "qa_start_filename": "1673884712.453442.pkl",
                "qa_end_filename": "1673884794.548095.pkl"
            }
        },
        {
            "id": "SHORT_37a3097f-a357-4af3-8a84-244e1b767ddf",
            "length_category": "SHORT",
            "length": 75.75372624397278,
            "start_time": 1673884729.145201,
            "end_time": 1673884804.8989272,
            "file_info": {
                "qa_start_filename": "1673884727.646265.pkl",
                "qa_end_filename": "1673884803.548804.pkl"
            }
        },
        {
            "id": "SHORT_31d323c2-930f-4111-85b0-d92e960ee600",
            "length_category": "SHORT",
            "length": 75.16009044647217,
            "start_time": 1673884478.7676463,
            "end_time": 1673884553.9277368,
            "file_info": {
                "qa_start_filename": "1673884477.317517.pkl",
                "qa_end_filename": "1673884552.52802.pkl"
            }
        },
        {
            "id": "SHORT_bbfb623d-89d7-4698-9e91-be03c2720fc8",
            "length_category": "SHORT",
            "length": 96.30728960037231,
            "start_time": 1673884874.1044726,
            "end_time": 1673884970.4117622,
            "file_info": {
                "qa_start_filename": "1673884872.65435.pkl",
                "qa_end_filename": "1673884969.063178.pkl"
            }
        },
        {
            "id": "SHORT_f20ba66d-74e4-4e2e-9a91-ac2576f16e0a",
            "length_category": "SHORT",
            "length": 66.90055441856384,
            "start_time": 1673884934.110338,
            "end_time": 1673885001.0108924,
            "file_info": {
                "qa_start_filename": "1673884932.660223.pkl",
                "qa_end_filename": "1673884999.657634.pkl"
            }
        },
        {
            "id": "SHORT_a29d9195-acc1-46ea-a225-95816e21e802",
            "length_category": "SHORT",
            "length": 57.45535612106323,
            "start_time": 1673884738.4428275,
            "end_time": 1673884795.8981836,
            "file_info": {
                "qa_start_filename": "1673884736.94361.pkl",
                "qa_end_filename": "1673884794.548095.pkl"
            }
        },
        {
            "id": "SHORT_103d708a-b002-415c-ab49-ff02f654c490",
            "length_category": "SHORT",
            "length": 30.550694704055786,
            "start_time": 1673884955.2116244,
            "end_time": 1673884985.762319,
            "file_info": {
                "qa_start_filename": "1673884953.761652.pkl",
                "qa_end_filename": "1673884984.361195.pkl"
            }
        },
        {
            "id": "SHORT_426931a9-038a-48a3-a27b-0f7b12948a81",
            "length_category": "SHORT",
            "length": 72.10592246055603,
            "start_time": 1673884823.0006893,
            "end_time": 1673884895.1066117,
            "file_info": {
                "qa_start_filename": "1673884821.550341.pkl",
                "qa_end_filename": "1673884893.756429.pkl"
            }
        },
        {
            "id": "SHORT_b928a4aa-a1fb-4161-ad8c-78e6f1e78eca",
            "length_category": "SHORT",
            "length": 99.05873370170593,
            "start_time": 1673884838.0518606,
            "end_time": 1673884937.1105943,
            "file_info": {
                "qa_start_filename": "1673884836.552372.pkl",
                "qa_end_filename": "1673884935.76041.pkl"
            }
        },
        {
            "id": "SHORT_21548fa5-15ca-4f06-923e-a99b0fb2253a",
            "length_category": "SHORT",
            "length": 36.699074029922485,
            "start_time": 1673884967.3617322,
            "end_time": 1673885004.0608063,
            "file_info": {
                "qa_start_filename": "1673884965.861486.pkl",
                "qa_end_filename": "1673885002.66134.pkl"
            }
        }
    ]
}